MANIFEST.in
setup.cfg
setup.py
countries/__init__.py
countries/models.py
countries/fixtures/default_countries.json
countries/tests/__init__.py
countries/tests/factories.py
countries/tests/test_models.py
incuna_countries.egg-info/PKG-INFO
incuna_countries.egg-info/SOURCES.txt
incuna_countries.egg-info/dependency_links.txt
incuna_countries.egg-info/top_level.txt
test_project/__init__.py
test_project/manage.py
test_project/runner.py
test_project/settings.py
test_project/wsgi.py