Metadata-Version: 1.0
Name: incuna-countries
Version: 1.1.1
Summary: Countries model and fixtures.
Home-page: http://incuna.com/
Author: Incuna Ltd
Author-email: dev@incuna.com
License: UNKNOWN
Platform: UNKNOWN
